Axha/Axha.py
Axha/__init__.py
Axha-1.8.2.dist-info/METADATA
Axha-1.8.2.dist-info/WHEEL
Axha-1.8.2.dist-info/top_level.txt
Axha-1.8.2.dist-info/RECORD
