Metadata-Version: 2.1
Name: Axha
Version: 1.8.2
Summary: TNSA AXHA IS A VOICE ASSISTANT MODULE USED TO DEVELOP AI VOICE ASSISTANT EASILY.
Home-page: UNKNOWN
Author: TNSA
Author-email: thishyakethabimalla@gmail.com
License: UNKNOWN
Platform: UNKNOWN
